<?xml version="1.0" encoding="utf-8"?>
<!DOCTYPE hibernate-mapping PUBLIC "-//Hibernate/Hibernate Mapping DTD 3.0//EN"
"http://hibernate.sourceforge.net/hibernate-mapping-3.0.dtd">
<!-- 
    Mapping file autogenerated by MyEclipse Persistence Tools
-->
<hibernate-mapping>
    <class name="com.zfgt.orm.Platform" table="platform" >
        <id name="id" type="java.lang.Long">
            <column name="id" />
<!--             <generator class="identity" />
 -->        </id>
        <property name="totalMoney" type="java.lang.Double">
            <column name="total_money" default="0">
                <comment>发布产品总额</comment>
            </column>
        </property>
        <property name="totalProfit" type="java.lang.Double">
            <column name="total_profit" default="0">
                <comment>总收益</comment>
            </column>
        </property>
        <property name="collectMoney" type="java.lang.Double">
            <column name="collect_money" default="0">
                <comment>已募集总金额</comment>
            </column>
        </property>
        <property name="totalCoupon" type="java.lang.Double">
            <column name="total_coupon" default="0">
                <comment>赠送的投资券总金额</comment>
            </column>
        </property>
        <property name="useCoupon" type="java.lang.Double">
            <column name="use_coupon" default="0">
                <comment>有效使用投资券的总金额</comment>
            </column>
        </property>
        <property name="registerCount" type="java.lang.Integer">
            <column name="register_count" default="0">
                <comment>注册人数</comment>
            </column>
        </property>
        <property name="insertTime" type="java.util.Date">
            <column name="insert_time" length="19" >
                <comment>插入时间</comment>
            </column>
        </property>
        <property name="updateTime" type="java.util.Date">
            <column name="update_time" length="19">
                <comment>更新时间</comment>
            </column>
        </property>
         <property name="freshmanCoupon" type="java.lang.Double">
            <column name="freshman_coupon" default="0">
                <comment>新手仅有一次投资机会的投资券</comment>
            </column>
        </property>
        <property name="virtualMoney" type="java.lang.Double">
            <column name="virtual_money" default="0">
                <comment>虚拟总额</comment>
            </column>
        </property>        
        <property name="totalCoin" type="java.lang.Long">
            <column name="total_coin" default="0">
            </column>
        </property>
        <property name="payCoin" type="java.lang.Long">
            <column name="pay_coin" default="0">
            </column>
        </property>
        <property name="leftCoin" type="java.lang.Long">
            <column name="left_coin" default="0">
            </column>
        </property>
    </class>
</hibernate-mapping>
